AsciidocWriter/__init__.py
AsciidocWriter/asciidoc_writer_utils.py
AsciidocWriter/document.py
AsciidocWriter/plot.py
AsciidocWriter/section.py
AsciidocWriter/table.py
asciidocwriter-0.0.3.3.dist-info/LICENSE
asciidocwriter-0.0.3.3.dist-info/METADATA
asciidocwriter-0.0.3.3.dist-info/WHEEL
asciidocwriter-0.0.3.3.dist-info/top_level.txt
asciidocwriter-0.0.3.3.dist-info/RECORD
