Metadata-Version: 2.1
Name: asciidocwriter
Version: 0.0.3.3
Summary: Asciidoctor generator
Home-page: https://github.com/vidigalp/asciidocwriter
Author: vidigalp
Author-email: pedro.vidigal@instaclustr.com
License: UNKNOWN
Platform: UNKNOWN
License-File: LICENSE
Requires-Dist: numpy
Requires-Dist: pandas
Requires-Dist: python-dateutil
Requires-Dist: pytz
Requires-Dist: six
Requires-Dist: tqdm
